apschedulersocket/__init__.py
apschedulersocket/schedulers.py
apschedulersocket/tests/__init__.py
APSchedulerSocket-0.4.2.dist-info/LICENSE
APSchedulerSocket-0.4.2.dist-info/METADATA
APSchedulerSocket-0.4.2.dist-info/WHEEL
APSchedulerSocket-0.4.2.dist-info/entry_points.txt
APSchedulerSocket-0.4.2.dist-info/top_level.txt
APSchedulerSocket-0.4.2.dist-info/RECORD
