Metadata-Version: 2.1
Name: APSchedulerSocket
Version: 0.4.2
Summary: The purpose of the application is to solve the problem of having a unique 'APScheduler' object for a multithreaded application. The project aims to easily implement a client-server architecture to control the scheduled processes. Another great advantage is that you can use the scheduler in distributed processes or servers.
Home-page: UNKNOWN
Author: Rodrigo Ristow
Author-email: rodrigo@maxttor.com
License: BSD
Platform: UNKNOWN
Classifier: Programming Language :: Python
Requires-Dist: setuptools
Requires-Dist: APScheduler
Provides-Extra: development
Requires-Dist: zest.releaser ; extra == 'development'
Requires-Dist: check-manifest ; extra == 'development'
Provides-Extra: test
Requires-Dist: nose ; extra == 'test'
Requires-Dist: nose-selecttests ; extra == 'test'
Requires-Dist: coverage ; extra == 'test'
Requires-Dist: unittest2 ; extra == 'test'
Requires-Dist: flake8 ; extra == 'test'
